oscope_scpi/__init__.py
oscope_scpi/dso.py
oscope_scpi/exr.py
oscope_scpi/keysight.py
oscope_scpi/mxr.py
oscope_scpi/oscilloscope.py
oscope_scpi/scpi.py
oscope_scpi/uxr.py
oscope_scpi-0.1.13.dist-info/LICENSE
oscope_scpi-0.1.13.dist-info/METADATA
oscope_scpi-0.1.13.dist-info/WHEEL
oscope_scpi-0.1.13.dist-info/top_level.txt
oscope_scpi-0.1.13.dist-info/RECORD
