Metadata-Version: 2.1
Name: oscope-scpi
Version: 0.1.13
Summary: Control of Oscilloscopes with SCPI command sets like Keysight MSO-X/DSO-X 3000A/3000T, UXR, MXR and EXR Series through python via PyVisa
Home-page: https://github.com/sgoadhouse/oscope-scpi
Author: Stephen Goadhouse
Author-email: sgoadhouse@virginia.edu
Maintainer: Stephen Goadhouse
Maintainer-email: sgoadhouse@virginia.edu
License: MIT
Keywords: HP,Agilent,Keysight,MSO3000,MSOX3000,DSO3000,DSOX3000,MXR,MXR058A,EXR,UXR,UXR0334A,PyVISA,VISA,SCPI,INSTRUMENT
Platform: UNKNOWN
Classifier: Development Status :: 4 - Beta
Classifier: Intended Audience :: Developers
Classifier: Intended Audience :: Education
Classifier: Intended Audience :: Science/Research
Classifier: License :: OSI Approved :: MIT License
Classifier: Programming Language :: Python
Classifier: Topic :: Scientific/Engineering
Classifier: Topic :: Scientific/Engineering :: Physics
Classifier: Topic :: Software Development
Classifier: Topic :: Software Development :: Libraries
Classifier: Topic :: Software Development :: Libraries :: Python Modules
Requires-Python: >=3.6
License-File: LICENSE
Requires-Dist: pyvisa (>=1.11.3)
Requires-Dist: pyvisa-py (>=0.5.2)
Requires-Dist: argparse
Requires-Dist: QuantiPhy (>=2.3.0)
Requires-Dist: numpy (==1.19.5) ; python_version < "3.8"
Requires-Dist: numpy (>=1.19.5) ; python_version >= "3.8"
